python_sample_package_with_data/__init__.py
python_sample_package_with_data_aitirga-0.0.3.data/scripts/python-sample-package-with-data
python_sample_package_with_data_aitirga-0.0.3.dist-info/METADATA
python_sample_package_with_data_aitirga-0.0.3.dist-info/WHEEL
python_sample_package_with_data_aitirga-0.0.3.dist-info/RECORD
