Metadata-Version: 2.1
Name: python-sample-package-with-data-aitirga
Version: 0.0.3
Summary: My short description
Home-page: https://github.com/aitirga/python-sample-package-with-data-aitirga
Author: Aitor Iraola
License: UNKNOWN
Platform: UNKNOWN
